imdb_server.py
iflow_mcp_imdb_mcp_server-1.0.3.dist-info/licenses/LICENSE
iflow_mcp_imdb_mcp_server-1.0.3.dist-info/METADATA
iflow_mcp_imdb_mcp_server-1.0.3.dist-info/WHEEL
iflow_mcp_imdb_mcp_server-1.0.3.dist-info/entry_points.txt
iflow_mcp_imdb_mcp_server-1.0.3.dist-info/top_level.txt
iflow_mcp_imdb_mcp_server-1.0.3.dist-info/RECORD
