Metadata-Version: 2.4
Name: iflow-mcp_imdb-mcp-server
Version: 1.0.3
Summary: A Python server implementing Model Context Protocol (MCP) for movie and TV show information using the IMDb API service
Author-email: uzaysozen <uzaysozen@example.com>
License: MIT
Classifier: Development Status :: 4 - Beta
Classifier: Intended Audience :: Developers
Classifier: License :: OSI Approved :: MIT License
Classifier: Programming Language :: Python :: 3
Classifier: Programming Language :: Python :: 3.13
Requires-Python: >=3.10
License-File: LICENSE
Requires-Dist: requests
Requires-Dist: mcp[cli]<=1.10.1
Dynamic: license-file
